geometric_theory_of_diffraction/Cylindric2DPhantom.py
geometric_theory_of_diffraction-0.0.1.dist-info/LICENSE
geometric_theory_of_diffraction-0.0.1.dist-info/METADATA
geometric_theory_of_diffraction-0.0.1.dist-info/WHEEL
geometric_theory_of_diffraction-0.0.1.dist-info/top_level.txt
geometric_theory_of_diffraction-0.0.1.dist-info/RECORD
