Metadata-Version: 2.1
Name: geometric-theory-of-diffraction
Version: 0.0.1
Summary: Geometric theory of diffraction models.
Author: Alex
Project-URL: Homepage, https://github.com/AlexanderMarinsek/geometric-theory-of-diffraction
Classifier: Programming Language :: Python :: 3
Classifier: License :: OSI Approved :: GNU General Public License v3 (GPLv3)
Classifier: Operating System :: OS Independent
Requires-Python: >=3.7
License-File: LICENSE
